.travis.yml
AUTHORS
ChangeLog
Makefile
README.md
setup.cfg
setup.py
silpa_common/__init__.py
silpa_common/charmap.py
silpa_common/langdetect.py
silpa_common.egg-info/PKG-INFO
silpa_common.egg-info/SOURCES.txt
silpa_common.egg-info/dependency_links.txt
silpa_common.egg-info/not-zip-safe
silpa_common.egg-info/top_level.txt
tests/test_langdetect.py