Metadata-Version: 1.1
Name: silpa-common
Version: 0.2
Summary: Common functions for SILPA and related modules
Home-page: https://silpa.org.in
Author: SILPA Developers
Author-email: silpa-discuss@nongnu.org
License: LGPL-2.1+
Platform: UNKNOWN
Classifier: Development Status :: 4 - Beta
Classifier: License :: DFSG approved
Classifier: License :: OSI Approved :: GNU Lesser General Public License v2 or later (LGPLv2+)
Classifier: Operating System :: OS Independent
Classifier: Intended Audience :: Developers
Classifier: Intended Audience :: Information Technology
Classifier: Programming Language :: Python
